colfi/__init__.py
colfi/cosmic_params.py
colfi/data_processor.py
colfi/data_simulator.py
colfi/element.py
colfi/fcnet_ann.py
colfi/fcnet_g.py
colfi/fcnet_mdn.py
colfi/models_ann.py
colfi/models_g.py
colfi/models_mdn.py
colfi/models_mg.py
colfi/nde.py
colfi/nodeframe.py
colfi/plotter.py
colfi/sequence.py
colfi/space_updater.py
colfi/utils.py
colfi/__pycache__/__init__.cpython-38.pyc
colfi/__pycache__/cosmic_params.cpython-38.pyc
colfi/__pycache__/data_processor.cpython-38.pyc
colfi/__pycache__/data_simulator.cpython-38.pyc
colfi/__pycache__/element.cpython-38.pyc
colfi/__pycache__/fcnet_ann.cpython-38.pyc
colfi/__pycache__/fcnet_g.cpython-38.pyc
colfi/__pycache__/fcnet_mdn.cpython-38.pyc
colfi/__pycache__/models_ann.cpython-38.pyc
colfi/__pycache__/models_g.cpython-38.pyc
colfi/__pycache__/models_mdn.cpython-38.pyc
colfi/__pycache__/nde.cpython-38.pyc
colfi/__pycache__/nodeframe.cpython-38.pyc
colfi/__pycache__/plotter.cpython-38.pyc
colfi/__pycache__/sequence.cpython-38.pyc
colfi/__pycache__/space_updater.cpython-38.pyc
colfi/__pycache__/utils.cpython-38.pyc
colfi-0.6.2.data/data/Pantheon_SNe_NoName.txt
colfi-0.6.2.data/data/Pantheon_Systematic_Error_Matrix.npy
colfi-0.6.2.data/data/chain_pantheon_fwCDM_3params.npy
colfi-0.6.2.data/data/chain_pantheon_fwCDM_3params_cov.npy
examples/loader.py
examples/simulator.py
examples/SNe_BAO/_pred_sne_bao_NDEs.py
examples/SNe_BAO/_train_sne_bao_test.py
examples/SNe_BAO/train_sne_bao.py
examples/data/Pantheon_SNe_NoName.txt
examples/data/Pantheon_Systematic_Error_Matrix.npy
examples/data/chain_pantheon_fwCDM_3params.npy
examples/data/chain_pantheon_fwCDM_3params_cov.npy
examples/linear/_pred_linear_NDEs.py
examples/linear/_train_linear_test.py
examples/linear/train_linear.py
examples/pantheon/_pred_pantheon_fwCDM_steps.py
examples/pantheon/_train_pantheon_fwCDM_nde.py
examples/pantheon/train_pantheon_fwCDM_nde_steps.py
colfi-0.6.2.dist-info/LICENSE
colfi-0.6.2.dist-info/METADATA
colfi-0.6.2.dist-info/WHEEL
colfi-0.6.2.dist-info/top_level.txt
colfi-0.6.2.dist-info/RECORD
