Metadata-Version: 2.1
Name: colfi
Version: 0.6.2
Summary: Cosmological Likelihood-Free Inference with Neural Density Estimators
Home-page: 
Author: Guojian Wang
Author-email: gjwang2018@gmail.com
License: MIT
Keywords: pip,ANN,MDN,MNN
Platform: any
License-File: LICENSE
Requires-Dist: coplot>=0.1.3
Requires-Dist: smt>=1.0.0
Requires-Dist: pandas>=1.1.3
Requires-Dist: numpy>=1.19.5
Requires-Dist: scipy>=1.6.2
Requires-Dist: matplotlib>=3.4.1
